openapi_file_finder/__init__.py
openapi_file_finder/__main__.py
openapi_file_finder/config.py
openapi_file_finder/cli/__init__.py
openapi_file_finder/cli/check.py
openapi_file_finder/cli/find.py
openapi_file_finder/utils/composer.py
openapi_file_finder/utils/filesystem.py
openapi_file_finder/utils/snippet.py
openapi_file_finder/utils/validate.py
openapi_file_finder-0.1.7.dist-info/METADATA
openapi_file_finder-0.1.7.dist-info/WHEEL
openapi_file_finder-0.1.7.dist-info/entry_points.txt
openapi_file_finder-0.1.7.dist-info/top_level.txt
openapi_file_finder-0.1.7.dist-info/RECORD
