Metadata-Version: 2.4
Name: openapi-file-finder
Version: 0.1.7
Summary: Add your description here
Requires-Python: >=3.12
Requires-Dist: aiofiles>=24.1.0
Requires-Dist: pyyaml>=6.0.2
Requires-Dist: typer>=0.12.3
Requires-Dist: rich>=13.7.1
Requires-Dist: structlog>=24.1.0
